livetrader/__init__.py
livetrader/exceptions.py
livetrader/rpc.py
livetrader/utils.py
livetrader/market/__init__.py
livetrader/market/base.py
livetrader/market/cache.py
livetrader/market/dwx.py
livetrader/market/tdx.py
livetrader/trade/__init__.py
livetrader/trade/base.py
livetrader-0.1.dist-info/LICENSE
livetrader-0.1.dist-info/METADATA
livetrader-0.1.dist-info/WHEEL
livetrader-0.1.dist-info/top_level.txt
livetrader-0.1.dist-info/RECORD
