Metadata-Version: 2.1
Name: livetrader
Version: 0.1
Summary: A small and extendable framework for trading
Home-page: https://github.com/lookis/livetrader
Author: lookis<Jingsi Liu>
Author-email: lookisliu@gmail.com
License: UNKNOWN
Platform: UNKNOWN
Requires-Python: >=3.6
Requires-Dist: click
Requires-Dist: tzlocal
Requires-Dist: environs
Requires-Dist: zerorpc
Requires-Dist: pymongo
Requires-Dist: motor
